LICENSE
MANIFEST.in
README.rst
setup.py
dime/__init__.py
dime/dime.hy
dime.egg-info/PKG-INFO
dime.egg-info/SOURCES.txt
dime.egg-info/dependency_links.txt
dime.egg-info/entry_points.txt
dime.egg-info/requires.txt
dime.egg-info/top_level.txt