Metadata-Version: 1.1
Name: dime
Version: 0.1.3
Summary: Virtual Desktop time tracker
Home-page: https://github.com/lepisma/dime
Author: Abhinav Tushar
Author-email: abhinav.tushar.vs@gmail.com
License: UNKNOWN
Platform: UNKNOWN
Classifier: License :: OSI Approved :: GNU General Public License v3 (GPLv3)
Classifier: Natural Language :: English
Classifier: Programming Language :: Python
Classifier: Programming Language :: Python :: 3 :: Only
